numpri/numpri.py
numpri-1.0.dist-info/LICENSE
numpri-1.0.dist-info/METADATA
numpri-1.0.dist-info/WHEEL
numpri-1.0.dist-info/top_level.txt
numpri-1.0.dist-info/RECORD
