Metadata-Version: 2.1
Name: numpri
Version: 1.0
Summary: A tool to perform like a primo.
Home-page: UNKNOWN
Author: Carmen Fontcuberta
Author-email: cfontcuberta@gmail.com
License: GNU GPLv3
Keywords: mathematical operations  numpri
Platform: UNKNOWN
Classifier: Development Status :: 4 - Beta
Classifier: Intended Audience :: Developers
Classifier: Topic :: Utilities
Classifier: License :: OSI Approved :: GNU General Public License v3 (GPLv3)
Classifier: Programming Language :: Python :: 3
Classifier: Operating System :: OS Independent
License-File: LICENSE
